LICENSE
ansible_vault_rotate/__init__.py
ansible_vault_rotate/cli/__init__.py
ansible_vault_rotate/cli/cli_args.py
ansible_vault_rotate/cli/config.py
ansible_vault_rotate/cli/glob.py
ansible_vault_rotate/cli/logging.py
ansible_vault_rotate/cli/rotator.py
ansible_vault_rotate/cli/run.py
ansible_vault_rotate/cli/tui.py
ansible_vault_rotate/match/__init__.py
ansible_vault_rotate/match/find.py
ansible_vault_rotate/match/test_find.py
ansible_vault_rotate/vault/__init__.py
ansible_vault_rotate/vault/detect.py
ansible_vault_rotate/vault/file.py
ansible_vault_rotate/vault/string.py
ansible_vault_rotate/vault/util.py
ansible_vault_rotate/vault/vault_source.py
ansible_vault_rotate-2.1.0.dist-info/LICENSE
ansible_vault_rotate-2.1.0.dist-info/METADATA
ansible_vault_rotate-2.1.0.dist-info/WHEEL
ansible_vault_rotate-2.1.0.dist-info/entry_points.txt
ansible_vault_rotate-2.1.0.dist-info/RECORD
