Metadata-Version: 2.1
Name: ansible-vault-rotate
Version: 2.1.0
Summary: Advanced Python CLI to rotate the secret used for ansible vault inline secrets and files in a project
Home-page: https://github.com/trustedshops-public/python-ansible-vault-rotate
License: MIT
Author: Timo Reymann
Author-email: Timo.Reymann@trustedshops.de
Requires-Python: >=3.9,<4.0
Classifier: Development Status :: 5 - Production/Stable
Classifier: Environment :: Console
Classifier: Environment :: MacOS X
Classifier: Framework :: Ansible
Classifier: Intended Audience :: Developers
Classifier: Intended Audience :: System Administrators
Classifier: License :: OSI Approved :: MIT License
Classifier: Operating System :: POSIX
Classifier: Operating System :: Unix
Classifier: Programming Language :: Python :: 3
Classifier: Programming Language :: Python :: 3.9
Classifier: Programming Language :: Python :: 3.10
Classifier: Programming Language :: Python :: 3.11
Classifier: Programming Language :: Python :: 3.12
Requires-Dist: ansible-core (>=2.9.0,<3.0.0)
Requires-Dist: inquirerpy (>=0.3.4,<0.4.0)
Project-URL: Bug Tracker, https://github.com/trustedshops-public/python-ansible-vault-rotate/issues
Project-URL: Repository, https://github.com/trustedshops-public/python-ansible-vault-rotate
